sql_grader/__init__.py
sql_grader/problem.py
sql_grader/settings.py
sql_grader/xblocks.py
sql_grader/datasets/rating.sql
sql_grader/datasets/social.sql
sql_grader/mixins/__init__.py
sql_grader/mixins/dates.py
sql_grader/mixins/fragment.py
sql_grader/mixins/grading.py
sql_grader/mixins/scenario.py
sql_grader/scenarios/SQL-Labs.xml
sql_grader/scenarios/SQL-Lectures.xml
sql_grader/static/view.css
sql_grader/static/view.js
sql_grader/static/view.less
sql_grader/static/codemirror/addon/edit/matchbrackets.js
sql_grader/static/codemirror/addon/hint/show-hint.css
sql_grader/static/codemirror/addon/hint/show-hint.js
sql_grader/static/codemirror/addon/hint/sql-hint.js
sql_grader/static/codemirror/lib/codemirror.css
sql_grader/static/codemirror/lib/codemirror.js
sql_grader/static/codemirror/mode/sql.js
sql_grader/templates/view.html
sql_grader/tests/__init__.py
sql_grader/tests/test_display.py
sql_grader/tests/test_problem.py
sql_grader/tests/test_workbench.py
sql_grader/translations/config.yaml
xblock_sql_grader-1.2.0.dist-info/LICENSE
xblock_sql_grader-1.2.0.dist-info/METADATA
xblock_sql_grader-1.2.0.dist-info/WHEEL
xblock_sql_grader-1.2.0.dist-info/entry_points.txt
xblock_sql_grader-1.2.0.dist-info/top_level.txt
xblock_sql_grader-1.2.0.dist-info/RECORD
