Metadata-Version: 2.1
Name: xblock-sql-grader
Version: 1.2.0
Summary: SQL Grader XBlock
License: AGPLv3
Classifier: Development Status :: 5 - Production/Stable
Classifier: Framework :: Django
Classifier: Framework :: Django :: 4.2
Classifier: Framework :: Django :: 5.2
Classifier: Intended Audience :: Developers
Classifier: License :: OSI Approved :: Apache Software License
Classifier: Natural Language :: English
Classifier: Programming Language :: Python :: 3
Classifier: Programming Language :: Python :: 3.11
Classifier: Programming Language :: Python :: 3.12
License-File: LICENSE
Requires-Dist: Django
Requires-Dist: XBlock
Requires-Dist: edx-codejail
